setup.cfg
setup.py
package_pl/__init__.py
package_pl/random.py
package_pl.egg-info/PKG-INFO
package_pl.egg-info/SOURCES.txt
package_pl.egg-info/dependency_links.txt
package_pl.egg-info/top_level.txt