Metadata-Version: 2.1
Name: package-pl
Version: 0.0
Summary: NaN
Home-page: UNKNOWN
Author-email: mikael_kodehode@gmail.com
License: UNKNOWN
Platform: UNKNOWN
